code_exec/__init__.py
code_exec/checker.py
code_exec/executor.py
code_exec-0.0.2.dist-info/LICENSE
code_exec-0.0.2.dist-info/METADATA
code_exec-0.0.2.dist-info/WHEEL
code_exec-0.0.2.dist-info/top_level.txt
code_exec-0.0.2.dist-info/RECORD
