Metadata-Version: 2.1
Name: code-exec
Version: 0.0.2
Summary: A small tool to execute python code more safely
Author-email: zimolab1995 <zimolab@aliyun.com>
Project-URL: Homepage, https://gitee.com/zimolab1995/code_exec
Project-URL: Bug Tracker, https://gitee.com/zimolab1995/code_exec/issues
Classifier: Programming Language :: Python :: 3
Classifier: License :: OSI Approved :: MIT License
Classifier: Operating System :: OS Independent
Requires-Python: >=3.7
License-File: LICENSE
